{"name":"checkErrorMessageAtFailedAuthentication","testCaseName":"com.tests.AuthenticationTests","testSteps":[{"number":1,"description":"Click sign in button","duration":4690,"startTime":1490959541195,"screenshots":[{"screenshot":"76f852479e27a450980711b2d848b309.png"},{"screenshot":"efd380b2ad2493664b0b8252506c328c.png"}],"result":"SUCCESS","precondition":false},{"number":2,"description":"Check error message at failed authentication: admin@yahoo.ro, $%^\u0026*()_","duration":2166,"startTime":1490959545886,"screenshots":[{"screenshot":"5be1e2450d864a1b5d4bd4633f26bc22.png"}],"result":"SUCCESS","precondition":false}],"userStory":{"id":"com.tests.AuthenticationTests","storyName":"Authentication tests","storyClassName":"com.tests.AuthenticationTests","path":"com.tests","type":"story"},"featureTag":{"name":"Tests/Authentication tests","type":"story"},"title":"Check error message at failed authentication","tags":[{"name":"Tests/Authentication tests","type":"story"}],"startTime":1490959533808,"duration":14255,"sessionId":"312879f7-3488-496c-8b3c-56953e7d8cea","driver":"firefox","manual":false,"testSource":"JUnit","result":"SUCCESS"}